[
  {
    "no": "1",
    "name": "Lokomotiva Marketing SH.P.K.",
    "tradeName": "Lokomotiva Marketing",
    "businessNo": "812034841",
    "municipality": "Prishtinë",
    "businessType": "Shoqëri me përgjegjësi të kufizuara",
    "status": "Regjistruar",
    "companyUrl": "https://arbk.rks-gov.net/page.aspx?id=1,38,245930",
    "category": "7312 - Publiciteti përmes mediave"
  },
  {
    "no": "2",
    "name": "3SD SH.P.K.",
    "tradeName": "3SD",
    "businessNo": "812012714",
    "municipality": "Prishtinë",
    "businessType": "Shoqëri me përgjegjësi të kufizuara",
    "status": "Regjistruar",
    "companyUrl": "https://arbk.rks-gov.net/page.aspx?id=1,38,243700",
    "category": "7312 - Publiciteti përmes mediave"
  },
  {
    "no": "3",
    "name": "DFUSIONE L.L.C.",
    "tradeName": "DFUSIONE",
    "businessNo": "811996175",
    "municipality": "Prishtinë",
    "businessType": "Shoqëri me përgjegjësi të kufizuara",
    "status": "Regjistruar",
    "companyUrl": "https://arbk.rks-gov.net/page.aspx?id=1,38,242034",
    "category": "7312 - Publiciteti përmes mediave"
  },
  {
    "no": "4",
    "name": "Alien Vision L.L.C.",
    "tradeName": "///",
    "businessNo": "811988792",
    "municipality": "Prishtinë",
    "businessType": "Shoqëri me përgjegjësi të kufizuara",
    "status": "Regjistruar",
    "companyUrl": "https://arbk.rks-gov.net/page.aspx?id=1,38,241292",
    "category": "7312 - Publiciteti përmes mediave"
  },
  {
    "no": "5",
    "name": "AM LTD  L.L.C.",
    "tradeName": "///",
    "businessNo": "811982322",
    "municipality": "Prishtinë",
    "businessType": "Shoqëri me përgjegjësi të kufizuara",
    "status": "Regjistruar",
    "companyUrl": "https://arbk.rks-gov.net/page.aspx?id=1,38,240640",
    "category": "7312 - Publiciteti përmes mediave"
  },
  {
    "no": "6",
    "name": "GROWUP ADVERTISING L.L.C.",
    "tradeName": "GROWUP ADVERTISING",
    "businessNo": "811963801",
    "municipality": "Prishtinë",
    "businessType": "Shoqëri me përgjegjësi të kufizuara",
    "status": "Regjistruar",
    "companyUrl": "https://arbk.rks-gov.net/page.aspx?id=1,38,237781",
    "category": "7312 - Publiciteti përmes mediave"
  },
  {
    "no": "7",
    "name": "SPOTLIGHT  L.L.C.",
    "tradeName": "SPOTLIGHT",
    "businessNo": "811951319",
    "municipality": "Vushtrri",
    "businessType": "Shoqëri me përgjegjësi të kufizuara",
    "status": "Regjistruar",
    "companyUrl": "https://arbk.rks-gov.net/page.aspx?id=1,38,234520",
    "category": "7312 - Publiciteti përmes mediave"
  },
  {
    "no": "8",
    "name": "LLAFE TGRAVE SH.P.K.",
    "tradeName": "LLAFE TGRAVE",
    "businessNo": "811942706",
    "municipality": "Gjilan",
    "businessType": "Shoqëri me përgjegjësi të kufizuara",
    "status": "Regjistruar",
    "companyUrl": "https://arbk.rks-gov.net/page.aspx?id=1,38,232664",
    "category": "7312 - Publiciteti përmes mediave"
  },
  {
    "no": "9",
    "name": "Gent Fandaj B.I.",
    "tradeName": "Digicenter",
    "businessNo": "811941766",
    "municipality": "Suharekë",
    "businessType": "Biznes individual",
    "status": "Shuar",
    "companyUrl": "https://arbk.rks-gov.net/page.aspx?id=1,38,231571",
    "category": "7312 - Publiciteti përmes mediave"
  },
  {
    "no": "10",
    "name": "Gjej SH.P.K.",
    "tradeName": "///",
    "businessNo": "811941576",
    "municipality": "Prishtinë",
    "businessType": "Shoqëri me përgjegjësi të kufizuara",
    "status": "Regjistruar",
    "companyUrl": "https://arbk.rks-gov.net/page.aspx?id=1,38,231552",
    "category": "7312 - Publiciteti përmes mediave"
  },
  {
    "no": "11",
    "name": "PRINDERIMI SH.P.K.",
    "tradeName": "PRINDERIMI",
    "businessNo": "811940239",
    "municipality": "Prishtinë",
    "businessType": "Shoqëri me përgjegjësi të kufizuara",
    "status": "Regjistruar",
    "companyUrl": "https://arbk.rks-gov.net/page.aspx?id=1,38,231417",
    "category": "7312 - Publiciteti përmes mediave"
  },
  {
    "no": "12",
    "name": "Reditë Limani B.I.",
    "tradeName": "///",
    "businessNo": "811939365",
    "municipality": "Prishtinë",
    "businessType": "Biznes individual",
    "status": "Regjistruar",
    "companyUrl": "https://arbk.rks-gov.net/page.aspx?id=1,38,231330",
    "category": "7312 - Publiciteti përmes mediave"
  },
  {
    "no": "13",
    "name": "Butterfly Touch L.L.C.",
    "tradeName": "Butterfly Touch",
    "businessNo": "811935975",
    "municipality": "Prishtinë",
    "businessType": "Shoqëri me përgjegjësi të kufizuara",
    "status": "Regjistruar",
    "companyUrl": "https://arbk.rks-gov.net/page.aspx?id=1,38,230990",
    "category": "7312 - Publiciteti përmes mediave"
  },
  {
    "no": "14",
    "name": "Nora Thaçi B.I.",
    "tradeName": "Throne Creative Agency",
    "businessNo": "811934919",
    "municipality": "Fushë Kosovë",
    "businessType": "Biznes individual",
    "status": "Regjistruar",
    "companyUrl": "https://arbk.rks-gov.net/page.aspx?id=1,38,230884",
    "category": "7312 - Publiciteti përmes mediave"
  },
  {
    "no": "15",
    "name": "Zest Marketing Agency L.L.C.",
    "tradeName": "Zest Marketing Agency",
    "businessNo": "811921578",
    "municipality": "Prishtinë",
    "businessType": "Shoqëri me përgjegjësi të kufizuara",
    "status": "Regjistruar",
    "companyUrl": "https://arbk.rks-gov.net/page.aspx?id=1,38,229533",
    "category": "7312 - Publiciteti përmes mediave"
  },
  {
    "no": "16",
    "name": "Reklamohu SH.P.K.",
    "tradeName": "///",
    "businessNo": "811920306",
    "municipality": "Prishtinë",
    "businessType": "Shoqëri me përgjegjësi të kufizuara",
    "status": "Regjistruar",
    "companyUrl": "https://arbk.rks-gov.net/page.aspx?id=1,38,229406",
    "category": "7312 - Publiciteti përmes mediave"
  },
  {
    "no": "17",
    "name": "Eagle Managment  SH.P.K.",
    "tradeName": "Eagle Managment",
    "businessNo": "811910993",
    "municipality": "Prishtinë",
    "businessType": "Shoqëri me përgjegjësi të kufizuara",
    "status": "Regjistruar",
    "companyUrl": "https://arbk.rks-gov.net/page.aspx?id=1,38,227490",
    "category": "7312 - Publiciteti përmes mediave"
  },
  {
    "no": "18",
    "name": "SOLIN DIGITAL SH.P.K.",
    "tradeName": "SOLIN DIGITAL",
    "businessNo": "811905340",
    "municipality": "Prishtinë",
    "businessType": "Shoqëri me përgjegjësi të kufizuara",
    "status": "Regjistruar",
    "companyUrl": "https://arbk.rks-gov.net/page.aspx?id=1,38,225936",
    "category": "7312 - Publiciteti përmes mediave"
  },
  {
    "no": "19",
    "name": "EVENTAJA L.L.C.",
    "tradeName": "///",
    "businessNo": "811903641",
    "municipality": "Prishtinë",
    "businessType": "Shoqëri me përgjegjësi të kufizuara",
    "status": "Regjistruar",
    "companyUrl": "https://arbk.rks-gov.net/page.aspx?id=1,38,225766",
    "category": "7312 - Publiciteti përmes mediave"
  },
  {
    "no": "20",
    "name": "GROWZILLAS GROUP L.L.C.",
    "tradeName": "///",
    "businessNo": "811898850",
    "municipality": "Prishtinë",
    "businessType": "Shoqëri me përgjegjësi të kufizuara",
    "status": "Regjistruar",
    "companyUrl": "https://arbk.rks-gov.net/page.aspx?id=1,38,225284",
    "category": "7312 - Publiciteti përmes mediave"
  },
  {
    "no": "21",
    "name": "LVL UP SH.P.K.",
    "tradeName": "LVL UP SHPK",
    "businessNo": "811891193",
    "municipality": "Prishtinë",
    "businessType": "Shoqëri me përgjegjësi të kufizuara",
    "status": "Regjistruar",
    "companyUrl": "https://arbk.rks-gov.net/page.aspx?id=1,38,224511",
    "category": "7312 - Publiciteti përmes mediave"
  },
  {
    "no": "22",
    "name": "AnM Creative L.L.C.",
    "tradeName": "AnM Creative",
    "businessNo": "811878563",
    "municipality": "Gjilan",
    "businessType": "Shoqëri me përgjegjësi të kufizuara",
    "status": "Regjistruar",
    "companyUrl": "https://arbk.rks-gov.net/page.aspx?id=1,38,222229",
    "category": "7312 - Publiciteti përmes mediave"
  },
  {
    "no": "23",
    "name": "Eris Veliu B.I.",
    "tradeName": "///",
    "businessNo": "811876541",
    "municipality": "Prishtinë",
    "businessType": "Biznes individual",
    "status": "Regjistruar",
    "companyUrl": "https://arbk.rks-gov.net/page.aspx?id=1,38,222024",
    "category": "7312 - Publiciteti përmes mediave"
  },
  {
    "no": "24",
    "name": "Dardania Consulting L.L.C.",
    "tradeName": "Dardania Consulting",
    "businessNo": "811869778",
    "municipality": "Prishtinë",
    "businessType": "Shoqëri me përgjegjësi të kufizuara",
    "status": "Regjistruar",
    "companyUrl": "https://arbk.rks-gov.net/page.aspx?id=1,38,221345",
    "category": "7312 - Publiciteti përmes mediave"
  },
  {
    "no": "25",
    "name": "Instinct L.L.C.",
    "tradeName": "///",
    "businessNo": "811848805",
    "municipality": "Prishtinë",
    "businessType": "Shoqëri me përgjegjësi të kufizuara",
    "status": "Regjistruar",
    "companyUrl": "https://arbk.rks-gov.net/page.aspx?id=1,38,219228",
    "category": "7312 - Publiciteti përmes mediave"
  },
  {
    "no": "26",
    "name": "Juns Film SH.P.K.",
    "tradeName": "Juns Film",
    "businessNo": "811848475",
    "municipality": "Obiliq",
    "businessType": "Shoqëri me përgjegjësi të kufizuara",
    "status": "Regjistruar",
    "companyUrl": "https://arbk.rks-gov.net/page.aspx?id=1,38,219195",
    "category": "7312 - Publiciteti përmes mediave"
  },
  {
    "no": "27",
    "name": "Think B Group SH.P.K.",
    "tradeName": "Think B Group",
    "businessNo": "811592262",
    "municipality": "Prishtinë",
    "businessType": "Shoqëri me përgjegjësi të kufizuara",
    "status": "Regjistruar",
    "companyUrl": "https://arbk.rks-gov.net/page.aspx?id=1,38,218956",
    "category": "7312 - Publiciteti përmes mediave"
  },
  {
    "no": "28",
    "name": "VS motors SH.P.K.",
    "tradeName": "VS motors",
    "businessNo": "811591256",
    "municipality": "Prishtinë",
    "businessType": "Shoqëri me përgjegjësi të kufizuara",
    "status": "Regjistruar",
    "companyUrl": "https://arbk.rks-gov.net/page.aspx?id=1,38,218856",
    "category": "7312 - Publiciteti përmes mediave"
  },
  {
    "no": "29",
    "name": "Arijanit Kastrati B.I.",
    "tradeName": "GROWUP AD",
    "businessNo": "811590018",
    "municipality": "Rahovec",
    "businessType": "Biznes individual",
    "status": "Regjistruar",
    "companyUrl": "https://arbk.rks-gov.net/page.aspx?id=1,38,218732",
    "category": "7312 - Publiciteti përmes mediave"
  },
  {
    "no": "30",
    "name": "HOVA Group L.L.C.",
    "tradeName": "///",
    "businessNo": "811589011",
    "municipality": "Prishtinë",
    "businessType": "Shoqëri me përgjegjësi të kufizuara",
    "status": "Regjistruar",
    "companyUrl": "https://arbk.rks-gov.net/page.aspx?id=1,38,218632",
    "category": "7312 - Publiciteti përmes mediave"
  },
  {
    "no": "31",
    "name": "Arton Muçolli B.I.",
    "tradeName": "Digit Media",
    "businessNo": "811575052",
    "municipality": "Prishtinë",
    "businessType": "Biznes individual",
    "status": "Regjistruar",
    "companyUrl": "https://arbk.rks-gov.net/page.aspx?id=1,38,217298",
    "category": "7312 - Publiciteti përmes mediave"
  },
  {
    "no": "32",
    "name": "Arsim Kokollari B.I.",
    "tradeName": "Focus Studio Creative",
    "businessNo": "811569782",
    "municipality": "Prishtinë",
    "businessType": "Biznes individual",
    "status": "Regjistruar",
    "companyUrl": "https://arbk.rks-gov.net/page.aspx?id=1,38,216772",
    "category": "7312 - Publiciteti përmes mediave"
  },
  {
    "no": "33",
    "name": "SmallTalk L.L.C.",
    "tradeName": "///",
    "businessNo": "811565293",
    "municipality": "Prishtinë",
    "businessType": "Shoqëri me përgjegjësi të kufizuara",
    "status": "Regjistruar",
    "companyUrl": "https://arbk.rks-gov.net/page.aspx?id=1,38,216325",
    "category": "7312 - Publiciteti përmes mediave"
  },
  {
    "no": "34",
    "name": "Sharr Mountains L.L.C.",
    "tradeName": "Sharr Mountains",
    "businessNo": "811517971",
    "municipality": "Gjilan",
    "businessType": "Shoqëri me përgjegjësi të kufizuara",
    "status": "Regjistruar",
    "companyUrl": "https://arbk.rks-gov.net/page.aspx?id=1,38,214650",
    "category": "7312 - Publiciteti përmes mediave"
  },
  {
    "no": "35",
    "name": "ArkivaPress L.L.C.",
    "tradeName": "ArkivaPress",
    "businessNo": "811506867",
    "municipality": "Prishtinë",
    "businessType": "Shoqëri me përgjegjësi të kufizuara",
    "status": "Regjistruar",
    "companyUrl": "https://arbk.rks-gov.net/page.aspx?id=1,38,213894",
    "category": "7312 - Publiciteti përmes mediave"
  },
  {
    "no": "36",
    "name": "Growzillas Academy L.L.C.",
    "tradeName": "///",
    "businessNo": "811504811",
    "municipality": "Prishtinë",
    "businessType": "Shoqëri me përgjegjësi të kufizuara",
    "status": "Regjistruar",
    "companyUrl": "https://arbk.rks-gov.net/page.aspx?id=1,38,213699",
    "category": "7312 - Publiciteti përmes mediave"
  },
  {
    "no": "37",
    "name": "CINC L.L.C.",
    "tradeName": "///",
    "businessNo": "811494864",
    "municipality": "Prishtinë",
    "businessType": "Shoqëri me përgjegjësi të kufizuara",
    "status": "Regjistruar",
    "companyUrl": "https://arbk.rks-gov.net/page.aspx?id=1,38,212757",
    "category": "7312 - Publiciteti përmes mediave"
  },
  {
    "no": "38",
    "name": "S3 MEDIA PRODUCTION  SH.P.K.",
    "tradeName": "///",
    "businessNo": "811483982",
    "municipality": "Prishtinë",
    "businessType": "Shoqëri me përgjegjësi të kufizuara",
    "status": "Regjistruar",
    "companyUrl": "https://arbk.rks-gov.net/page.aspx?id=1,38,211792",
    "category": "7312 - Publiciteti përmes mediave"
  },
  {
    "no": "39",
    "name": "Blq SH.P.K.",
    "tradeName": "///",
    "businessNo": "811481267",
    "municipality": "Pejë",
    "businessType": "Shoqëri me përgjegjësi të kufizuara",
    "status": "Regjistruar",
    "companyUrl": "https://arbk.rks-gov.net/page.aspx?id=1,38,211531",
    "category": "7312 - Publiciteti përmes mediave"
  },
  {
    "no": "40",
    "name": "BLUE ADVERTSING L.L.C.",
    "tradeName": "BLUE ADVERTSING",
    "businessNo": "811480805",
    "municipality": "Prishtinë",
    "businessType": "Shoqëri me përgjegjësi të kufizuara",
    "status": "Regjistruar",
    "companyUrl": "https://arbk.rks-gov.net/page.aspx?id=1,38,211486",
    "category": "7312 - Publiciteti përmes mediave"
  },
  {
    "no": "41",
    "name": "Agon Halili B.I.",
    "tradeName": "Hashtag agency",
    "businessNo": "811458456",
    "municipality": "Ferizaj",
    "businessType": "Biznes individual",
    "status": "Regjistruar",
    "companyUrl": "https://arbk.rks-gov.net/page.aspx?id=1,38,209512",
    "category": "7312 - Publiciteti përmes mediave"
  },
  {
    "no": "42",
    "name": "Regera L.L.C.",
    "tradeName": "Regera",
    "businessNo": "811438234",
    "municipality": "Ferizaj",
    "businessType": "Shoqëri me përgjegjësi të kufizuara",
    "status": "Regjistruar",
    "companyUrl": "https://arbk.rks-gov.net/page.aspx?id=1,38,207591",
    "category": "7312 - Publiciteti përmes mediave"
  },
  {
    "no": "43",
    "name": "Helix Media Grup SH.P.K.",
    "tradeName": "Helix Media Grup",
    "businessNo": "811436444",
    "municipality": "Prizren",
    "businessType": "Shoqëri me përgjegjësi të kufizuara",
    "status": "Regjistruar",
    "companyUrl": "https://arbk.rks-gov.net/page.aspx?id=1,38,207422",
    "category": "7312 - Publiciteti përmes mediave"
  },
  {
    "no": "44",
    "name": "Pinguini Marketing L.L.C.",
    "tradeName": "Pinguini Marketing",
    "businessNo": "811426651",
    "municipality": "Prishtinë",
    "businessType": "Shoqëri me përgjegjësi të kufizuara",
    "status": "Regjistruar",
    "companyUrl": "https://arbk.rks-gov.net/page.aspx?id=1,38,206490",
    "category": "7312 - Publiciteti përmes mediave"
  },
  {
    "no": "45",
    "name": "Inner Space SH.P.K.",
    "tradeName": "Inner Space",
    "businessNo": "811418179",
    "municipality": "Prishtinë",
    "businessType": "Shoqëri me përgjegjësi të kufizuara",
    "status": "Regjistruar",
    "companyUrl": "https://arbk.rks-gov.net/page.aspx?id=1,38,205697",
    "category": "7312 - Publiciteti përmes mediave"
  },
  {
    "no": "46",
    "name": "Mimozë Lakna B.I.",
    "tradeName": "Bota marketing",
    "businessNo": "811399337",
    "municipality": "Prishtinë",
    "businessType": "Biznes individual",
    "status": "Regjistruar",
    "companyUrl": "https://arbk.rks-gov.net/page.aspx?id=1,38,203962",
    "category": "7312 - Publiciteti përmes mediave"
  },
  {
    "no": "47",
    "name": "Veranda Gashi B.I.",
    "tradeName": "Fashioon Home VIP",
    "businessNo": "811398743",
    "municipality": "Pejë",
    "businessType": "Biznes individual",
    "status": "Regjistruar",
    "companyUrl": "https://arbk.rks-gov.net/page.aspx?id=1,38,203910",
    "category": "7312 - Publiciteti përmes mediave"
  },
  {
    "no": "48",
    "name": "24 ore info SH.P.K.",
    "tradeName": "24 ore info",
    "businessNo": "811396531",
    "municipality": "Prishtinë",
    "businessType": "Shoqëri me përgjegjësi të kufizuara",
    "status": "Regjistruar",
    "companyUrl": "https://arbk.rks-gov.net/page.aspx?id=1,38,203712",
    "category": "7312 - Publiciteti përmes mediave"
  },
  {
    "no": "49",
    "name": "Growzillas L.L.C.",
    "tradeName": "Growzillas",
    "businessNo": "811389809",
    "municipality": "Prishtinë",
    "businessType": "Shoqëri me përgjegjësi të kufizuara",
    "status": "Regjistruar",
    "companyUrl": "https://arbk.rks-gov.net/page.aspx?id=1,38,203094",
    "category": "7312 - Publiciteti përmes mediave"
  },
  {
    "no": "50",
    "name": "Pranvera Selimi B.I.",
    "tradeName": "Blond Almond",
    "businessNo": "811382473",
    "municipality": "Prishtinë",
    "businessType": "Biznes individual",
    "status": "Regjistruar",
    "companyUrl": "https://arbk.rks-gov.net/page.aspx?id=1,38,202448",
    "category": "7312 - Publiciteti përmes mediave"
  },
  {
    "no": "51",
    "name": "Xhevat Belaj B.I.",
    "tradeName": "///",
    "businessNo": "811379438",
    "municipality": "Prishtinë",
    "businessType": "Biznes individual",
    "status": "Regjistruar",
    "companyUrl": "https://arbk.rks-gov.net/page.aspx?id=1,38,202197",
    "category": "7312 - Publiciteti përmes mediave"
  },
  {
    "no": "52",
    "name": "Anita Uka B.I.",
    "tradeName": "Influencers Agency",
    "businessNo": "811361451",
    "municipality": "Mitrovicë",
    "businessType": "Biznes individual",
    "status": "Regjistruar",
    "companyUrl": "https://arbk.rks-gov.net/page.aspx?id=1,38,199635",
    "category": "7312 - Publiciteti përmes mediave"
  },
  {
    "no": "53",
    "name": "Blue Marketing SH.P.K.",
    "tradeName": "///",
    "businessNo": "811344241",
    "municipality": "Prishtinë",
    "businessType": "Shoqëri me përgjegjësi të kufizuara",
    "status": "Regjistruar",
    "companyUrl": "https://arbk.rks-gov.net/page.aspx?id=1,38,197149",
    "category": "7312 - Publiciteti përmes mediave"
  },
  {
    "no": "54",
    "name": "Option One SH.P.K.",
    "tradeName": "///",
    "businessNo": "811326348",
    "municipality": "Prishtinë",
    "businessType": "Shoqëri me përgjegjësi të kufizuara",
    "status": "Regjistruar",
    "companyUrl": "https://arbk.rks-gov.net/page.aspx?id=1,38,195748",
    "category": "7312 - Publiciteti përmes mediave"
  },
  {
    "no": "55",
    "name": "Egzon I. Rexhepi B.I.",
    "tradeName": "AllofRenders",
    "businessNo": "811323451",
    "municipality": "Podujevë",
    "businessType": "Biznes individual",
    "status": "Regjistruar",
    "companyUrl": "https://arbk.rks-gov.net/page.aspx?id=1,38,195547",
    "category": "7312 - Publiciteti përmes mediave"
  },
  {
    "no": "56",
    "name": "Hyda Kelmendi B.I.",
    "tradeName": "FRAME PRO",
    "businessNo": "811308289",
    "municipality": "Obiliq",
    "businessType": "Biznes individual",
    "status": "Regjistruar",
    "companyUrl": "https://arbk.rks-gov.net/page.aspx?id=1,38,194406",
    "category": "7312 - Publiciteti përmes mediave"
  },
  {
    "no": "57",
    "name": "5M AGENCY SH.P.K.",
    "tradeName": "5M AGENCY",
    "businessNo": "811302877",
    "municipality": "Prizren",
    "businessType": "Shoqëri me përgjegjësi të kufizuara",
    "status": "Regjistruar",
    "companyUrl": "https://arbk.rks-gov.net/page.aspx?id=1,38,193986",
    "category": "7312 - Publiciteti përmes mediave"
  },
  {
    "no": "58",
    "name": "PAC STUDIO SH.P.K.",
    "tradeName": "///",
    "businessNo": "811276676",
    "municipality": "Ferizaj",
    "businessType": "Shoqëri me përgjegjësi të kufizuara",
    "status": "Regjistruar",
    "companyUrl": "https://arbk.rks-gov.net/page.aspx?id=1,38,192057",
    "category": "7312 - Publiciteti përmes mediave"
  },
  {
    "no": "59",
    "name": "Fatmir R. Bytyqi B.I.",
    "tradeName": "///",
    "businessNo": "811266536",
    "municipality": "Fushë Kosovë",
    "businessType": "Biznes individual",
    "status": "Pasiv",
    "companyUrl": "https://arbk.rks-gov.net/page.aspx?id=1,38,191073",
    "category": "7312 - Publiciteti përmes mediave"
  },
  {
    "no": "60",
    "name": "ANEL MARKETING B.I.",
    "tradeName": "N.SH. \" ANEL MARKETING \"",
    "businessNo": "71185044",
    "municipality": "Gjilan",
    "businessType": "Biznes individual",
    "status": "Shuar",
    "companyUrl": "https://arbk.rks-gov.net/page.aspx?id=1,38,182671",
    "category": "7312 - Publiciteti përmes mediave"
  },
  {
    "no": "61",
    "name": "Alban Nebiu B.I.",
    "tradeName": "N.SH.  \" WORLD WIDE MARKETING \"",
    "businessNo": "811214353",
    "municipality": "Gjilan",
    "businessType": "Biznes individual",
    "status": "Pasiv",
    "companyUrl": "https://arbk.rks-gov.net/page.aspx?id=1,38,182631",
    "category": "7312 - Publiciteti përmes mediave"
  },
  {
    "no": "62",
    "name": "Digital Pika SH.P.K.",
    "tradeName": "///",
    "businessNo": "810134312",
    "municipality": "Gjilan",
    "businessType": "Shoqëri me përgjegjësi të kufizuara",
    "status": "Pasiv",
    "companyUrl": "https://arbk.rks-gov.net/page.aspx?id=1,38,178900",
    "category": "7312 - Publiciteti përmes mediave"
  },
  {
    "no": "63",
    "name": "Bardha Ibishi B.I.",
    "tradeName": "///",
    "businessNo": "810129868",
    "municipality": "Mitrovicë Veriore",
    "businessType": "Biznes individual",
    "status": "Pasiv",
    "companyUrl": "https://arbk.rks-gov.net/page.aspx?id=1,38,175476",
    "category": "7312 - Publiciteti përmes mediave"
  },
  {
    "no": "64",
    "name": "EMAX SOLUTIONS D.O.O.",
    "tradeName": "///",
    "businessNo": "810072380",
    "municipality": "Mitrovicë Veriore",
    "businessType": "Shoqëri me përgjegjësi të kufizuara",
    "status": "Regjistruar",
    "companyUrl": "https://arbk.rks-gov.net/page.aspx?id=1,38,174978",
    "category": "7312 - Publiciteti përmes mediave"
  },
  {
    "no": "65",
    "name": "Aleksandar Terentic I.B.",
    "tradeName": "ALEKSANDAR TERENTIC  I.B.",
    "businessNo": "811118331",
    "municipality": "Vushtrri",
    "businessType": "Biznes individual",
    "status": "Regjistruar",
    "companyUrl": "https://arbk.rks-gov.net/page.aspx?id=1,38,167369",
    "category": "7312 - Publiciteti përmes mediave"
  },
  {
    "no": "66",
    "name": "FESTINA RTV SH.P.K.",
    "tradeName": "///",
    "businessNo": "811054113",
    "municipality": "Ferizaj",
    "businessType": "Shoqëri me përgjegjësi të kufizuara",
    "status": "Pasiv",
    "companyUrl": "https://arbk.rks-gov.net/page.aspx?id=1,38,156562",
    "category": "7312 - Publiciteti përmes mediave"
  },
  {
    "no": "67",
    "name": "BUBRRECAT STUDIO L.L.C.",
    "tradeName": "///",
    "businessNo": "810184599",
    "municipality": "Prizren",
    "businessType": "Shoqëri me përgjegjësi të kufizuara",
    "status": "Regjistruar",
    "companyUrl": "https://arbk.rks-gov.net/page.aspx?id=1,38,143918",
    "category": "7312 - Publiciteti përmes mediave"
  },
  {
    "no": "68",
    "name": "Gentrit N. Gashi B.I.",
    "tradeName": "///",
    "businessNo": "810016495",
    "municipality": "Prishtinë",
    "businessType": "Biznes individual",
    "status": "Regjistruar",
    "companyUrl": "https://arbk.rks-gov.net/page.aspx?id=1,38,140378",
    "category": "7312 - Publiciteti përmes mediave"
  },
  {
    "no": "69",
    "name": "Valon Gërdovci B.I.",
    "tradeName": "///",
    "businessNo": "810009375",
    "municipality": "Prishtinë",
    "businessType": "Biznes individual",
    "status": "Pasiv",
    "companyUrl": "https://arbk.rks-gov.net/page.aspx?id=1,38,140335",
    "category": "7312 - Publiciteti përmes mediave"
  },
  {
    "no": "70",
    "name": "Active Ads & Marketing L.L.C.",
    "tradeName": "///",
    "businessNo": "810138512",
    "municipality": "Prishtinë",
    "businessType": "Shoqëri me përgjegjësi të kufizuara",
    "status": "Regjistruar",
    "companyUrl": "https://arbk.rks-gov.net/page.aspx?id=1,38,126830",
    "category": "7312 - Publiciteti përmes mediave"
  },
  {
    "no": "71",
    "name": "Double Trouble SH.P.K.",
    "tradeName": "///",
    "businessNo": "810100909",
    "municipality": "Prishtinë",
    "businessType": "Shoqëri me përgjegjësi të kufizuara",
    "status": "Pasiv",
    "companyUrl": "https://arbk.rks-gov.net/page.aspx?id=1,38,126074",
    "category": "7312 - Publiciteti përmes mediave"
  },
  {
    "no": "72",
    "name": "BB Media SH.P.K.",
    "tradeName": "///",
    "businessNo": "810874679",
    "municipality": "Prishtinë",
    "businessType": "Shoqëri me përgjegjësi të kufizuara",
    "status": "Regjistruar",
    "companyUrl": "https://arbk.rks-gov.net/page.aspx?id=1,38,123872",
    "category": "7312 - Publiciteti përmes mediave"
  },
  {
    "no": "73",
    "name": "FRONTONLINE SH.P.K.",
    "tradeName": "///",
    "businessNo": "810871469",
    "municipality": "Prishtinë",
    "businessType": "Shoqëri me përgjegjësi të kufizuara",
    "status": "Regjistruar",
    "companyUrl": "https://arbk.rks-gov.net/page.aspx?id=1,38,123542",
    "category": "7312 - Publiciteti përmes mediave"
  },
  {
    "no": "74",
    "name": "BALKAN PROGRESS CENTER L.L.C.",
    "tradeName": "///",
    "businessNo": "810871162",
    "municipality": "Prishtinë",
    "businessType": "Shoqëri me përgjegjësi të kufizuara",
    "status": "Regjistruar",
    "companyUrl": "https://arbk.rks-gov.net/page.aspx?id=1,38,123512",
    "category": "7312 - Publiciteti përmes mediave"
  },
  {
    "no": "75",
    "name": "Events And Press SH.P.K.",
    "tradeName": "///",
    "businessNo": "810855554",
    "municipality": "Prishtinë",
    "businessType": "Shoqëri me përgjegjësi të kufizuara",
    "status": "Pasiv",
    "companyUrl": "https://arbk.rks-gov.net/page.aspx?id=1,38,121881",
    "category": "7312 - Publiciteti përmes mediave"
  },
  {
    "no": "76",
    "name": "VIZIONI 360 SH.P.K.",
    "tradeName": "///",
    "businessNo": "810854449",
    "municipality": "Prishtinë",
    "businessType": "Shoqëri me përgjegjësi të kufizuara",
    "status": "Pasiv",
    "companyUrl": "https://arbk.rks-gov.net/page.aspx?id=1,38,121767",
    "category": "7312 - Publiciteti përmes mediave"
  },
  {
    "no": "77",
    "name": "Adonis Zejnullahu B.I.",
    "tradeName": "N.T.P. \" Zogu  Entertainment \"",
    "businessNo": "810787567",
    "municipality": "Podujevë",
    "businessType": "Biznes individual",
    "status": "Pasiv",
    "companyUrl": "https://arbk.rks-gov.net/page.aspx?id=1,38,114235",
    "category": "7312 - Publiciteti përmes mediave"
  },
  {
    "no": "78",
    "name": "AN MEDIA SH.P.K.",
    "tradeName": "///",
    "businessNo": "810776784",
    "municipality": "Podujevë",
    "businessType": "Shoqëri me përgjegjësi të kufizuara",
    "status": "Pasiv",
    "companyUrl": "https://arbk.rks-gov.net/page.aspx?id=1,38,112592",
    "category": "7312 - Publiciteti përmes mediave"
  },
  {
    "no": "79",
    "name": "Fit4You SH.P.K.",
    "tradeName": "///",
    "businessNo": "810712704",
    "municipality": "Lipjan",
    "businessType": "Shoqëri me përgjegjësi të kufizuara",
    "status": "Pasiv",
    "companyUrl": "https://arbk.rks-gov.net/page.aspx?id=1,38,102454",
    "category": "7312 - Publiciteti përmes mediave"
  },
  {
    "no": "80",
    "name": "GISUN L.L.C.",
    "tradeName": "///",
    "businessNo": "810156382",
    "municipality": "Mitrovicë",
    "businessType": "Shoqëri me përgjegjësi të kufizuara",
    "status": "Pasiv",
    "companyUrl": "https://arbk.rks-gov.net/page.aspx?id=1,38,70917",
    "category": "7312 - Publiciteti përmes mediave"
  },
  {
    "no": "81",
    "name": "ADCLICK SH.P.K.",
    "tradeName": "///",
    "businessNo": "810550427",
    "municipality": "Mitrovicë",
    "businessType": "Shoqëri me përgjegjësi të kufizuara",
    "status": "Pasiv",
    "companyUrl": "https://arbk.rks-gov.net/page.aspx?id=1,38,70567",
    "category": "7312 - Publiciteti përmes mediave"
  }
]
